udify/__init__.py
udify/dataset_readers/__init__.py
udify/dataset_readers/conll18_ud_eval.py
udify/dataset_readers/evaluate_2019_task2.py
udify/dataset_readers/lemma_edit.py
udify/dataset_readers/parser.py
udify/dataset_readers/sigmorphon_2019_task_2.py
udify/dataset_readers/universal_dependencies.py
udify/models/__init__.py
udify/models/dependency_decoder.py
udify/models/tag_decoder.py
udify/models/udify_model.py
udify/modules/__init__.py
udify/modules/bert_pretrained.py
udify/modules/residual_rnn.py
udify/modules/scalar_mix.py
udify/modules/text_field_embedder.py
udify/modules/token_characters_encoder.py
udify/optimizers/__init__.py
udify/optimizers/ulmfit_sqrt.py
udify/predictors/__init__.py
udify/predictors/predictor.py
udify/predictors/text_predictor.py
udify/util.py
unofficial_udify-0.3.0.dist-info/LICENSE
unofficial_udify-0.3.0.dist-info/WHEEL
unofficial_udify-0.3.0.dist-info/METADATA
unofficial_udify-0.3.0.dist-info/RECORD
