Metadata-Version: 2.1
Name: unofficial-udify
Version: 0.3.0
Summary: 
Author: Dan Kondratyuk
Requires-Python: >=3.6.1
Classifier: Programming Language :: Python :: 3
Classifier: Programming Language :: Python :: 3.7
Classifier: Programming Language :: Python :: 3.8
Classifier: Programming Language :: Python :: 3.9
Requires-Dist: allennlp (>=1.0.0,<2.0.0)
Requires-Dist: conllu (>=3.0,<4.0)
Requires-Dist: transformers (>=2.3.0,<3.0.0)
